harvey/__init__.py
harvey/get_tldr.py
harvey/harvey.py
harvey/licences_tldr.json
harvey/licenses.json
harvey/summary.json
harvey-0.0.5.dist-info/DESCRIPTION.rst
harvey-0.0.5.dist-info/METADATA
harvey-0.0.5.dist-info/RECORD
harvey-0.0.5.dist-info/WHEEL
harvey-0.0.5.dist-info/entry_points.txt
harvey-0.0.5.dist-info/metadata.json
harvey-0.0.5.dist-info/top_level.txt
