Metadata-Version: 2.0
Name: harvey
Version: 0.0.5
Summary: harvey helps you manage and choose license from command line
Home-page: https://github.com/architv/harvey
Author: Archit Verma
Author-email: architv07@gmail.com
License: MIT
Keywords: license,legal,github,command line,cli
Platform: UNKNOWN
Requires-Dist: colorama (==0.3.3)
Requires-Dist: docopt (>=0.6.2)
Requires-Dist: requests (>=2.8.0)
